{
  "title": "EmberJS Berlin Meetup",
  "url": "https://example.com/",
  "language": "en",
  "description": "EmberJS Berlin is a community of Ember developers and enthusiasts. Join our regular online and in-person meetups and learn more about Ember.",
  "feed": {
    "subtitle": "EmberJS Berlin is a community of Ember developers and enthusiasts. Join our regular online and in-person meetups and learn more about Ember.",
    "filename": "feed.xml",
    "path": "/feed/feed.xml",
    "id": "https://emberjsberlin.github.io"
  },
  "jsonfeed": {
    "path": "/feed/feed.json",
    "url": "https://emberjsberlin.github.io/feed/feed.json"
  },
  "author": {
    "name": "The EmberJS Berlin Org Team",
    "email": "emberjsberlin@gmail.com",
    "url": "https://emberjsberlin.github.io/about/"
  }
}
